{
  "id": "f71b343d-af55-40de-bf4b-ecb823785049",
  "title": "10mg: Sealed Estate",
  "storefront": "itch",
  "databaseId": "773883",
  "slug": "10mg-sealed-estate",
  "publisher": "10mg",
  "developer": "Gesinimo Games",
  "release_date": "2020-10-01",
  "genre": "Adventure, Indie",
  "languages": [
    "English"
  ],
  "game_modes": [
    "Single player"
  ],
  "size": "",
  "description": "A psychological horror game in which you are locked inside by a creature ready to hunt you down, whilst you figure out how to escape from the estate you have been locked inside. Who lived here? Who are the voices haunting your every step?",
  "vertical_artwork": "https://images.gog.com/29adcf722a8e7506fdf6196332fb60fd9ef76eb355b6f6ef42f3dac8521b6bd3.jpg?namespace=gamesdb",
  "banner_image": "https://steamcdn-a.akamaihd.net/steam/apps/1435480/library_hero.jpg",
  "icon_image": "https://steamcdn-a.akamaihd.net/steam/apps/1435480/capsule_231x87.jpg",
  "gog_url": "",
  "epic_url": "",
  "itch_url": "https://salmanshh.itch.io/10mg-sealed-estate",
  "steamId": "1435480",
  "pcgamingwiki_url": "",
  "protondb_url": "https://www.protondb.com/app/1435480",
  "requires_eos": false,
  "supports_eos": false,
  "epic_cloud_saves": false,
  "epic_achievements": false,
  "epic_offline_mode": false,
  "gog_cloud_saves": false,
  "controller_input": "keyboard-mouse",
  "requires_eac_runtime": false,
  "requires_battleye_runtime": false,
  "notes": "Works out of the box! May need to reset launch options if it doesn't launch on first attempt.",
  "date_tested": "Nov '25",
  "proton_version": "",
  "decky_rating": "not-supported",
  "standalone_rating": "green",
  "dependencies": "",
  "controller_config": "",
  "performance_notes": "",
  "known_issues": "",
  "set_executable": "",
  "required_launcher": "",
  "requires_account_setup": false,
  "account_type": "",
  "requires_verification": false,
  "must_be_online": false,
  "cant_test_linux": false,
  "community_layout": false,
  "is_featured": false
}
