{
  "id": "2533b514-a6fd-43df-b0a9-79318bcbee62",
  "title": "Amelie",
  "storefront": "itch",
  "databaseId": "1269964",
  "slug": "amelie",
  "publisher": "Two and a Half Studios",
  "developer": "Two and a Half Studios",
  "release_date": "2021-12-16",
  "genre": "Indie, Simulator, Visual Novel",
  "languages": [
    "English",
    "Simplified Chinese"
  ],
  "game_modes": [
    "Single player"
  ],
  "size": "",
  "description": "A psychological mystery yuri visual novel about a girl named Amelie. Forbidden from leaving the house, Amelie awaits the arrival of her long time penpal, Sofia, to her dear friend Lilika’s dismay. What secrets will Sofia unravel that were best kept buried?",
  "vertical_artwork": "https://images.gog.com/a4716ebbeb9f5658b29c1ab357eb5ef054465db8308250c313e0b7370f944d2b.jpg?namespace=gamesdb",
  "banner_image": "https://steamcdn-a.akamaihd.net/steam/apps/1835810/library_hero.jpg",
  "icon_image": "https://steamcdn-a.akamaihd.net/steam/apps/1835810/capsule_231x87.jpg",
  "gog_url": "",
  "epic_url": "",
  "itch_url": "https://twoandahalfstudios.itch.io/amelie",
  "steamId": "1835810",
  "pcgamingwiki_url": "https://www.pcgamingwiki.com/wiki/Amelie",
  "protondb_url": "https://www.protondb.com/app/1835810",
  "requires_eos": false,
  "supports_eos": false,
  "epic_cloud_saves": false,
  "epic_achievements": false,
  "epic_offline_mode": false,
  "gog_cloud_saves": false,
  "controller_input": "native",
  "requires_eac_runtime": false,
  "requires_battleye_runtime": false,
  "notes": "Works out of the box. You may need to reset launch options if it doesn't launch first go.",
  "date_tested": "Dec '25",
  "proton_version": "",
  "decky_rating": "not-supported",
  "standalone_rating": "green",
  "dependencies": "",
  "controller_config": "",
  "performance_notes": "",
  "known_issues": "",
  "set_executable": "",
  "required_launcher": "",
  "requires_account_setup": false,
  "account_type": "",
  "requires_verification": false,
  "must_be_online": false,
  "cant_test_linux": false,
  "community_layout": false,
  "is_featured": false
}
