{
  "id": "9289d33d-8fc6-4032-ac72-0aa315872b77",
  "title": "Betrayer",
  "storefront": "GOG",
  "protondb": "https://www.protondb.com/app/243120",
  "notes": "Native controller support **Decky Plugin: Works out of the box**. **2.0 Standalone: Works out of the box**.",
  "date_tested": "July '24",
  "proton_version": "",
  "dependencies": "",
  "controller_config": "Native Steam Deck Controls",
  "performance_notes": "",
  "known_issues": "",
  "decky_rating": "green",
  "standalone_rating": "green",
  "gog_url": "https://www.gog.com/en/game/betrayer",
  "steamId": "243120",
  "publisher": "NIL, NIL",
  "developer": "Blackpowder Games",
  "genre": "Adventure, Indie, Shooter",
  "description": "Betrayer is a first person action adventure game that takes you to the New World at the turn of the 17th century. The year is 1604. You sailed from England expecting to join a struggling colony on the coast of Virginia. Instead, you find only ghosts and mysteries. What catastrophe blighted the land and drained it of color and life?",
  "game_modes": [
    "Single player"
  ],
  "languages": [
    "English"
  ],
  "updated_at": "2025-08-01T04:08:36.964Z",
  "exported_at": "2025-08-13T20:50:39.614Z"
}