{
  "id": "e782e739-acd5-4df1-922c-9728d4f7a189",
  "title": "Empire of the Ants",
  "storefront": "GOG",
  "date_tested": "Nov '24",
  "decky_rating": "green",
  "standalone_rating": "green",
  "proton_version": "",
  "images": {
    "vertical_artwork": "https://images.gog.com/f4f570ab0f5e5da11a8cd3d4418688490d8dbecc8451496558d671c8258c8a1d.jpg?namespace=gamesdb",
    "banner_image": "https://images.gog.com/d237f9a6130f3546a61b19fdd59a0fc67a71f10f3b21c565d75dea13055ebff7.jpg?namespace=gamesdb",
    "icon_image": "https://images.gog.com/f4f570ab0f5e5da11a8cd3d4418688490d8dbecc8451496558d671c8258c8a1d.jpg?namespace=gamesdb",
    "verticalArtwork": "https://images.gog.com/f4f570ab0f5e5da11a8cd3d4418688490d8dbecc8451496558d671c8258c8a1d.jpg?namespace=gamesdb"
  },
  "publisher": "Microids",
  "developer": "Tower Five",
  "genre": "adventure, strategy, indie, real-time-strategy-rts",
  "releasedate": "",
  "description": "Embark on an epic journey into the infinitesimal in this photorealistic strategy game. Play as a fearless ant and guide your colony through the dangers of the forest.",
  "size": "",
  "epic_features": null,
  "dependencies": "",
  "controller_config": "Native Steam Deck Controls",
  "controller_input": "native",
  "set_executable": "",
  "required_launcher": "",
  "requires_account_setup": false,
  "account_type": "",
  "steamId": "2287330",
  "protondb": "https://www.protondb.com/app/2287330",
  "is_featured": false,
  "cant_test_linux": false,
  "notes": "Native controller support **Decky Plugin: Works out of the box**. **2.0 Standalone: Works out of the box**.",
  "performance_notes": "",
  "known_issues": "",
  "created_at": "2025-08-01T02:40:48.192Z",
  "updated_at": "2025-08-01T04:08:36.966Z"
}