{
  "id": "421b9172-2d9d-4878-9355-cf008003304a",
  "title": "MDK",
  "storefront": "GOG",
  "date_tested": "July '24",
  "decky_rating": "green",
  "standalone_rating": "green",
  "proton_version": "",
  "images": {
    "vertical_artwork": "https://images.gog.com/e8d1afb04a57c22b675c24e811040f46a7e6a0fae661609d68a9b4915d968994.jpg?namespace=gamesdb",
    "banner_image": "https://images.gog.com/c65d0f6c97ff8f1fcb1a22efb0547a55c40960a0b25cad310d1a91ec069dbe48.jpg?namespace=gamesdb",
    "icon_image": "https://images.gog.com/e8d1afb04a57c22b675c24e811040f46a7e6a0fae661609d68a9b4915d968994.jpg?namespace=gamesdb",
    "verticalArtwork": "https://images.gog.com/e8d1afb04a57c22b675c24e811040f46a7e6a0fae661609d68a9b4915d968994.jpg?namespace=gamesdb"
  },
  "publisher": "Playmates Interactive Entertainment, Interplay Entertainment",
  "developer": "Shiny Entertainment",
  "genre": "platform, shooter",
  "releasedate": "",
  "description": "The game tells the story of Kurt Hectic, a janitor who reluctantly must attempt to save Earth from an alien invasion of gigantic strip mining city-size vehicles named \"Minecrawlers\".",
  "size": "",
  "epic_features": null,
  "dependencies": "",
  "controller_config": "Native Steam Deck Controls",
  "controller_input": "native",
  "set_executable": "",
  "required_launcher": "",
  "requires_account_setup": false,
  "account_type": "",
  "steamId": "38450",
  "protondb": "https://www.protondb.com/app/38450",
  "is_featured": false,
  "cant_test_linux": false,
  "notes": "Native controller support **Decky Plugin: Works out of the box**. **2.0 Standalone: Works out of the box**.",
  "performance_notes": "",
  "known_issues": "",
  "created_at": "2025-08-01T02:40:48.192Z",
  "updated_at": "2025-08-01T04:08:36.968Z"
}