{
  "id": "65631a46-e1d8-44b2-9d60-480a1d754576",
  "title": "Raidborn",
  "storefront": "GOG",
  "databaseId": "2061161309",
  "slug": "raidborn",
  "publisher": "Phodex Games",
  "developer": "Phodex Games",
  "release_date": "2023-03-01",
  "genre": "role-playing, adventure, indie",
  "languages": [
    "English"
  ],
  "game_modes": [
    "Single player"
  ],
  "size": "",
  "description": "Enough of wasting precious time by walking eternal distances and engaging in endless dialogue? Want to get to the fun part quickly?",
  "vertical_artwork": "https://images.gog.com/a39bfb5c64224405cc42c70daa0f851b7101d8377d05cb41adc7d0d1ccbeb989.jpg?namespace=gamesdb",
  "banner_image": "https://images.gog.com/b0e310d6d8559a64417851fc9d78023fae0cfa58fbecd68fe02ad529116dc4f4.jpg?namespace=gamesdb",
  "icon_image": "https://images.gog.com/d35c975da5b438f044bd13aabd690189981ecb3dd415624e8f4bf4d024148791.jpg?namespace=gamesdb",
  "gog_url": "https://www.gog.com/en/game/raidborn",
  "epic_url": "",
  "itch_url": "",
  "steamId": "1546090",
  "hltb_url": "https://howlongtobeat.com/game/126805",
  "hltb_id": 126805,
  "hltb_main_extra": "16.5 hrs",
  "metacritic_score": null,
  "metacritic_url": "https://www.metacritic.com/game/raidborn/",
  "pcgamingwiki_url": "",
  "protondb_url": "https://www.protondb.com/app/1546090",
  "protondb_report_url": "",
  "protondb_report_date": "",
  "requires_eos": false,
  "supports_eos": false,
  "epic_cloud_saves": false,
  "epic_achievements": false,
  "epic_offline_mode": false,
  "gog_cloud_saves": false,
  "controller_input": "native",
  "requires_eac_runtime": false,
  "requires_battleye_runtime": false,
  "notes": "Works out of the box on the Decky plugin version. Early access.",
  "date_tested": "Nov '24",
  "proton_version": "",
  "decky_rating": "green",
  "standalone_rating": "unknown",
  "dependencies": "",
  "controller_config": "",
  "performance_notes": "",
  "known_issues": "",
  "set_executable": "",
  "required_launcher": "",
  "requires_account_setup": false,
  "account_type": "",
  "requires_verification": false,
  "must_be_online": false,
  "cant_test_linux": false,
  "community_layout": false,
  "is_featured": false
}
