{
  "id": "96ed4698-3490-4652-9098-58cac918df8d",
  "title": "Sherlock Holmes: Chapter One",
  "storefront": "GOG",
  "protondb": "https://www.protondb.com/app/1137300",
  "gog_url": "https://www.gog.com/en/game/sherlock_holmes_chapter_one",
  "epic_url": "",
  "itch_url": "",
  "pc_gaming_wiki_url": "",
  "notes": "Mouse-only controls. **Decky Plugin: Works out of the box**. **2.0 Standalone: Works out of the box**.",
  "date_tested": "Oct '24",
  "decky_rating": "green",
  "standalone_rating": "unknown",
  "proton_version": "",
  "dependencies": "",
  "controller_config": "",
  "performance_notes": "",
  "known_issues": "",
  "requires_eos": false,
  "supports_eos": false,
  "requires_verification": false,
  "epic_achievements": false,
  "epic_offline_mode": false,
  "must_be_online": false,
  "requires_eac_runtime": false,
  "requires_battleye_runtime": false,
  "required_launcher": "",
  "requires_account_setup": false,
  "account_type": "",
  "controller_input": "mouse-only",
  "community_layout": false,
  "cant_test_linux": false,
  "databaseId": "2094849865",
  "shortname": "2094849865",
  "publisher": "Frogwares",
  "developer": "Frogwares",
  "releasedate": "",
  "genre": "Adventure, Indie",
  "description": "In this story-driven detective thriller, a young Sherlock Holmes struggles to prove himself as he navigates an exotic, dangerous island in the Mediterranean to investigate the mystery of his mother's death.",
  "size": "",
  "vertical_artwork": "https://images.gog.com/2aa2c11ac93b4f44279a210c282544107e654c09e276234a72f2f54c077dc240.jpg?namespace=gamesdb",
  "banner_image": "https://images.gog.com/e1f5900921de222aee97305e10a2e2faf4783afe51630b515cb99290116d0c70.jpg?namespace=gamesdb",
  "icon_image": "https://images.gog.com/2aa2c11ac93b4f44279a210c282544107e654c09e276234a72f2f54c077dc240.jpg?namespace=gamesdb",
  "steamId": "1137300",
  "game_modes": [
    "Single player"
  ],
  "languages": [
    "English"
  ],
  "gog_cloud_saves": false,
  "gog_achievements": false,
  "tested": true,
  "owned": false,
  "is_featured": false,
  "created_at": "2025-08-01T02:40:48.192Z",
  "updated_at": "2025-08-11T08:06:52.064Z"
}