{
  "id": "f5b2d068-9f36-4abd-a1b9-dc3552c3e79c",
  "title": "Symphonia",
  "storefront": "GOG",
  "protondb": "https://www.protondb.com/app/1865960",
  "notes": "<strong>Works out of the box</strong> — no extra setup needed. Student Project, 2020.",
  "date_tested": "Dec '24",
  "proton_version": "",
  "dependencies": "",
  "controller_config": "Native Steam Deck Controls",
  "performance_notes": "",
  "known_issues": "",
  "decky_rating": "Perfect",
  "standalone_rating": "Perfect",
  "gog_url": "https://www.gog.com/en/game/symphonia_student_project_2020",
  "steamId": "1865960",
  "publisher": "Headup, Sunny Peak",
  "developer": "Headup, Sunny Peak",
  "genre": "Adventure, Indie, Platform, Music",
  "description": "Embody a violinist and awaken a gigantic, forsaken world in this highly poetic platformer! Using your violin and bow, move towards the core of the realm to understand your role in this universe and play the best Concerto!",
  "game_modes": [
    "Single player"
  ],
  "languages": [
    "English"
  ],
  "updated_at": "2025-08-01T04:08:36.969Z",
  "exported_at": "2025-08-13T20:50:39.623Z"
}