{
  "id": "aa1a2fc7-85e0-4dc6-a4bf-dd908fe161b8",
  "title": "20 Minutes Till Dawn",
  "storefront": "Epic",
  "protondb": "https://www.protondb.com/app/1966900",
  "protondb_report_url": "",
  "gog_url": "",
  "epic_url": "https://store.epicgames.com/en-US/p/20-minutes-till-dawn-be3305",
  "itch_url": "",
  "pc_gaming_wiki_url": "https://www.pcgamingwiki.com/wiki/20_Minutes_till_Dawn",
  "notes": "Works out of the box!",
  "date_tested": "July '25",
  "decky_rating": "green",
  "standalone_rating": "green",
  "proton_version": "",
  "dependencies": "",
  "controller_config": "",
  "performance_notes": "",
  "known_issues": "",
  "requires_eos": false,
  "supports_eos": false,
  "requires_verification": false,
  "epic_achievements": false,
  "epic_offline_mode": false,
  "must_be_online": false,
  "requires_eac_runtime": false,
  "requires_battleye_runtime": false,
  "required_launcher": "",
  "requires_account_setup": false,
  "account_type": "",
  "controller_input": "native",
  "community_layout": false,
  "cant_test_linux": false,
  "databaseId": "4656facc740742a39e265b026e13d075",
  "shortname": "4656facc740742a39e265b026e13d075",
  "publisher": "flanne",
  "developer": "flanne",
  "releasedate": "2024-01-02T16:00:00.000Z",
  "genre": "Action, Indie, Rogue-Lite",
  "description": "20 Minutes Till Dawn is a survival roguelite where endless hordes of creatures lurk from the dark. Craft an array of overpowering builds and eradicate waves of Lovecraftian nightmares. Will you be able to survive the night?",
  "size": "54.5 MB",
  "franchise": "",
  "tags_structured": [
    {
      "id": "1216",
      "name": "Action"
    },
    {
      "id": "21122",
      "name": "Diverse Characters"
    },
    {
      "id": "1188",
      "name": "RELAXING"
    },
    {
      "id": "9547",
      "name": "Windows"
    },
    {
      "id": "1263",
      "name": "Indie"
    },
    {
      "id": "21137",
      "name": "Unique Visuals"
    },
    {
      "id": "21138",
      "name": "Recommend this Game"
    },
    {
      "id": "21139",
      "name": "Amazing Characters"
    },
    {
      "id": "21109",
      "name": "Great Boss Battles"
    },
    {
      "id": "21141",
      "name": "Extremely Fun"
    },
    {
      "id": "1370",
      "name": "Single Player"
    },
    {
      "id": "1083",
      "name": "Rogue-Lite"
    },
    {
      "id": "21149",
      "name": "Quickly Understand the Controls"
    },
    {
      "id": "21119",
      "name": "Great for Beginners"
    }
  ],
  "genres_structured": [
    {
      "id": "1216",
      "name": "Action"
    },
    {
      "id": "1263",
      "name": "Indie"
    },
    {
      "id": "1083",
      "name": "Rogue-Lite"
    }
  ],
  "age_rating_summary": "ESRB Everyone 10+",
  "reviews_summary": null,
  "igdb_id": 199748,
  "igdb_url": "https://www.igdb.com/games/199748",
  "giveaway_events": [
    {
      "start": "2024-01-01T15:00:00.000Z",
      "end": "2024-01-02T15:00:00.000Z",
      "type": null,
      "id": "9758dccdbda54c1387f732d0d7d03b3b"
    }
  ],
  "was_free_before": true,
  "description_rich": "20 Minutes Till Dawn is a survival roguelite where endless hordes of creatures lurk from the dark. Craft an array of overpowering builds and eradicate waves of Lovecraftian nightmares. Will you be able to survive the night?",
  "use_rich_description": true,
  "vertical_artwork": "https://images.gog.com/dc6e09d21833f3696ca9d9ff3f9b9758e71d669ef1f912c084a99d5f078c13dc.jpg?namespace=gamesdb",
  "banner_image": "https://images.gog.com/a9496a68e60138bc54514978d4255d1bb41ccd69639cf6846fb8b52f2538ee6f.jpg?namespace=gamesdb",
  "icon_image": "https://images.gog.com/7a7a9f1aad41de777cd56d5d7ac272c2ed1983ec5ce8bce2c373f815dd12e6b3.jpg?namespace=gamesdb",
  "steamId": "1966900",
  "game_modes": [
    "Single player"
  ],
  "languages": [
    "English"
  ],
  "metacritic_score": null,
  "metacritic_url": "https://www.metacritic.com/game/20-minutes-till-dawn/",
  "hltb_id": 109172,
  "hltb_main": "3.7 hrs",
  "hltb_main_extra": "12.4 hrs",
  "hltb_completionist": "30.1 hrs",
  "hltb_url": "https://howlongtobeat.com/game/109172",
  "epic_cloud_saves": false,
  "tested": true,
  "owned": true,
  "is_featured": false,
  "blog_category": "",
  "created_at": "2025-08-01T02:40:48.200Z",
  "updated_at": "2026-04-25T02:41:47.571Z"
}