{
  "id": "44b91903-b6db-44e2-9be0-7ae119fb4878",
  "title": "Beyond Blue",
  "storefront": "Epic",
  "protondb": "https://www.protondb.com/app/883360",
  "protondb_report_url": "",
  "gog_url": "",
  "epic_url": "https://store.epicgames.com/en-US/p/beyond-blue",
  "itch_url": "",
  "pc_gaming_wiki_url": "https://www.pcgamingwiki.com/wiki/Beyond_Blue",
  "notes": "Works out of the box!",
  "date_tested": "Feb '25",
  "decky_rating": "green",
  "standalone_rating": "green",
  "proton_version": "",
  "dependencies": "",
  "controller_config": "Native Steam Deck Controls",
  "performance_notes": "",
  "known_issues": "",
  "requires_eos": true,
  "supports_eos": false,
  "requires_verification": false,
  "epic_achievements": false,
  "epic_offline_mode": false,
  "must_be_online": false,
  "requires_eac_runtime": false,
  "requires_battleye_runtime": false,
  "required_launcher": "",
  "requires_account_setup": false,
  "account_type": "",
  "controller_input": "native",
  "community_layout": false,
  "cant_test_linux": false,
  "databaseId": "3a0cae9455844390ad00505a704d641e",
  "shortname": "3a0cae9455844390ad00505a704d641e",
  "publisher": "E-Line Media",
  "developer": "E-Line Media",
  "release_date": "2020-06-11",
  "genre": "Casual, Adventure, Indie",
  "description": "Beyond Blue is a single-player narrative adventure that takes you deep into our planet’s beating blue heart.  Set in the near future, Beyond Blue explores the mysteries of our ocean through the eyes of Mirai, a deep-sea explorer and scientist. Become a part of a newly-formed r...",
  "size": "",
  "franchise": "",
  "tags_structured": [
    {
      "id": "1296",
      "name": "Casual"
    },
    {
      "id": "21894",
      "name": "Cloud Saves"
    },
    {
      "id": "1370",
      "name": "Single Player"
    },
    {
      "id": "9547",
      "name": "Windows"
    },
    {
      "id": "1117",
      "name": "Adventure"
    },
    {
      "id": "1263",
      "name": "Indie"
    }
  ],
  "genres_structured": [
    {
      "id": "1296",
      "name": "Casual"
    },
    {
      "id": "1117",
      "name": "Adventure"
    },
    {
      "id": "1263",
      "name": "Indie"
    }
  ],
  "age_rating_summary": "ESRB Everyone",
  "reviews_summary": null,
  "giveaway_events": [
    {
      "start": "2025-02-06T16:00:00.000Z",
      "end": "2025-02-13T16:00:00.000Z",
      "type": null,
      "id": "c3006006e4c74c4d8316ff09fb8dcc8d"
    },
    {
      "start": "2023-04-19T15:00:00.000Z",
      "end": "2023-04-26T15:00:00.000Z",
      "type": null,
      "id": "c3006006e4c74c4d8316ff09fb8dcc8d"
    }
  ],
  "was_free_before": true,
  "description_rich": "Beyond Blue is a single-player narrative adventure that takes you deep into our planet’s beating blue heart.  Set in the near future, Beyond Blue explores the mysteries of our ocean through the eyes of Mirai, a deep-sea explorer and scientist. Become a part of a newly-formed r...",
  "description_gog": "",
  "description_steam": "",
  "use_rich_description": true,
  "description_source": "",
  "gamesdb_game_id": "51306668528586328",
  "gamesdb_gog_id": "",
  "gamesdb_epic_id": "",
  "gamesdb_itch_id": "",
  "gamesdb_amazon_id": "",
  "vertical_artwork": "https://images.gog.com/d3fd49a913ef5db2e95cb7478cff44c4301a01198a94c93f1297cd15fc8b7c48.jpg?namespace=gamesdb",
  "banner_image": "https://images.gog.com/6a760d12b1f5b37e91be7f88ec50b40eb9cdbf9990b15093357f640ecc1cf689.jpg?namespace=gamesdb",
  "icon_image": "https://images.gog.com/f76a8d2b6fbc119c7e2cdb7e8d91715733dea569cdba83cef7bd407cd4e6ce2d.jpg?namespace=gamesdb",
  "steamId": "883360",
  "game_modes": [
    "Single player"
  ],
  "languages": [
    "English"
  ],
  "metacritic_score": 72,
  "metacritic_url": "https://www.metacritic.com/game/pc/beyond-blue?ftag=MCD-06-10aaa1f",
  "hltb_id": 77495,
  "hltb_main": "2.7 hrs",
  "hltb_main_extra": "4 hrs",
  "hltb_completionist": "5.4 hrs",
  "hltb_url": "https://howlongtobeat.com/game/77495",
  "epic_cloud_saves": true,
  "owned": true,
  "is_featured": false,
  "blog_category": "",
  "created_at": "2025-08-01T02:40:48.200Z",
  "updated_at": "2026-04-26T02:26:29.954Z"
}