{
  "id": "bef1f0b6-af9d-43fa-8509-4dc1e1f6ce47",
  "title": "Boxes: Lost Fragments",
  "storefront": "Epic",
  "databaseId": "cbb53ad616af4e93973aa73ea2b15733",
  "slug": "boxes-lost-fragments",
  "publisher": "Snapbreak Games",
  "developer": "Big Loop Studios",
  "release_date": "2026-02-26",
  "genre": "Casual, Puzzle, Adventure",
  "languages": [
    "English",
    "French",
    "Italian",
    "German",
    "Spanish - Spain",
    "Indonesian",
    "Japanese",
    "Korean",
    "Polish",
    "Portuguese - Portugal"
  ],
  "game_modes": [
    "Single player"
  ],
  "size": "",
  "age_rating_summary": "ESRB Everyone",
  "tags_structured": [
    {
      "id": "1296",
      "name": "Casual"
    },
    {
      "id": "1298",
      "name": "Puzzle"
    },
    {
      "id": "19847",
      "name": "Achievements"
    },
    {
      "id": "1370",
      "name": "Single Player"
    },
    {
      "id": "1117",
      "name": "Adventure"
    },
    {
      "id": "39070",
      "name": "iOS"
    }
  ],
  "genres_structured": [
    {
      "id": "1296",
      "name": "Casual"
    },
    {
      "id": "1298",
      "name": "Puzzle"
    },
    {
      "id": "1117",
      "name": "Adventure"
    }
  ],
  "description": "As a legendary thief, your next assignment lures you into a grand and lavish mansion. There you find a series of puzzle boxes, designed for an unknown purpose. What should have been a quick in-and-out, gradually turns into your own harrowing struggle for freedom and answers.",
  "vertical_artwork": "https://steamcdn-a.akamaihd.net/steam/apps/2019810/library_600x900.jpg",
  "banner_image": "https://steamcdn-a.akamaihd.net/steam/apps/2019810/library_hero.jpg",
  "icon_image": "https://steamcdn-a.akamaihd.net/steam/apps/2019810/capsule_231x87.jpg",
  "gog_url": "",
  "epic_url": "https://store.epicgames.com/en-US/p/boxes-lost-fragments-079041",
  "itch_url": "",
  "steamId": "2019810",
  "hltb_url": "https://howlongtobeat.com/game/144798",
  "hltb_id": 144798,
  "hltb_main": "3.8 hrs",
  "hltb_main_extra": "3.8 hrs",
  "hltb_completionist": "4 hrs",
  "metacritic_score": 84,
  "metacritic_url": "https://www.metacritic.com/game/boxes-lost-fragments/",
  "pcgamingwiki_url": "",
  "protondb_url": "https://www.protondb.com/app/2019810",
  "protondb_report_url": "",
  "protondb_report_date": "",
  "requires_eos": false,
  "supports_eos": false,
  "epic_cloud_saves": false,
  "epic_achievements": true,
  "epic_offline_mode": true,
  "gog_cloud_saves": false,
  "controller_input": "mouse-only",
  "requires_eac_runtime": false,
  "requires_battleye_runtime": false,
  "notes": "Works out of the box!",
  "date_tested": "Feb '26",
  "proton_version": "",
  "decky_rating": "green",
  "standalone_rating": "green",
  "dependencies": "",
  "controller_config": "",
  "performance_notes": "",
  "known_issues": "",
  "set_executable": "",
  "required_launcher": "",
  "requires_account_setup": false,
  "account_type": "",
  "requires_verification": false,
  "must_be_online": false,
  "cant_test_linux": false,
  "community_layout": false,
  "is_featured": false,
  "description_rich": "As a legendary thief, your next assignment lures you into a grand and lavish mansion. There you find a series of puzzle boxes, designed for an unknown purpose. What should have been a quick in-and-out, gradually turns into your own harrowing struggle for freedom and answers.",
  "use_rich_description": true
}
