{
  "id": "8d5fce39-8e06-48cb-80c4-fd158cba68ff",
  "title": "Freshly Frosted",
  "storefront": "Epic",
  "protondb": "https://www.protondb.com/app/1070790",
  "gog_url": "",
  "epic_url": "",
  "itch_url": "",
  "pc_gaming_wiki_url": "",
  "notes": "Works out of the box!",
  "date_tested": "July '24",
  "decky_rating": "green",
  "standalone_rating": "green",
  "proton_version": "",
  "dependencies": "",
  "controller_config": "Native Steam Deck Controls",
  "performance_notes": "",
  "known_issues": "",
  "requires_eos": false,
  "supports_eos": false,
  "requires_verification": false,
  "epic_achievements": true,
  "epic_offline_mode": false,
  "must_be_online": false,
  "requires_eac_runtime": false,
  "requires_battleye_runtime": false,
  "required_launcher": "",
  "requires_account_setup": false,
  "account_type": "",
  "controller_input": "native",
  "community_layout": false,
  "cant_test_linux": false,
  "databaseId": "c95f2c3e2e8b41f1bb9de3036e53f319",
  "shortname": "c95f2c3e2e8b41f1bb9de3036e53f319",
  "publisher": "The Quantum Astrophysicists Guild",
  "developer": "The Quantum Astrophysicists Guild",
  "releasedate": "2022-06-10T00:00:00+0000",
  "genre": "Strategy, Indie, Puzzle, Arcade, Simulator",
  "description": "Place conveyor belts to solve puzzles in the world's most adorable donut factory!",
  "size": "",
  "vertical_artwork": "https://images.gog.com/51988980e85d2c14df39ad2d2da730e2cfb0f77b372f231ea5a2f9da54223250.jpg?namespace=gamesdb",
  "banner_image": "https://images.gog.com/eba064f7bcb280867c493f0fd1138a04893cbc90a0bedf7cc051af4dc2a06eac.jpg?namespace=gamesdb",
  "icon_image": "https://images.gog.com/88586f350e622cd179e01a9507d5624e0d4ab3bb292c727d8d5047cfe6c6a3a5.jpg?namespace=gamesdb",
  "steamId": "1070790",
  "game_modes": [
    "Single player"
  ],
  "languages": [
    "English"
  ],
  "epic_cloud_saves": false,
  "tested": true,
  "owned": true,
  "is_featured": false,
  "blog_category": "",
  "created_at": "2025-08-01T02:40:48.200Z",
  "updated_at": "2025-08-05T21:42:29.673Z"
}