{
  "id": "9f0ad367-bdcb-4026-a517-968d1fb4818c",
  "title": "Just Die Already",
  "storefront": "Epic",
  "protondb": "https://www.protondb.com/app/979070",
  "gog_url": "",
  "epic_url": "",
  "itch_url": "",
  "notes": "Requires manual controller/key mapping. **Decky Plugin: Some tinkering required**. **2.0 Standalone: Some tinkering required**.",
  "date_tested": "July '25",
  "decky_rating": "yellow",
  "standalone_rating": "yellow",
  "proton_version": "",
  "dependencies": "",
  "controller_config": "",
  "performance_notes": "",
  "known_issues": "",
  "requires_eos": false,
  "supports_eos": false,
  "requires_verification": false,
  "epic_achievements": false,
  "epic_offline_mode": false,
  "must_be_online": false,
  "requires_eac_runtime": false,
  "requires_battleye_runtime": false,
  "required_launcher": "",
  "requires_account_setup": false,
  "account_type": "",
  "controller_input": "requires-mapping",
  "community_layout": false,
  "cant_test_linux": false,
  "databaseId": "06621054d7d24f44bf13e3c31c9ec05d",
  "shortname": "06621054d7d24f44bf13e3c31c9ec05d",
  "publisher": "Curve Digital, DoubleMoose Games",
  "developer": "DoubleMoose Games",
  "releasedate": "2021-05-20T00:00:00+0000",
  "genre": "Adventure, Indie, Platform, Simulator",
  "description": "Just Die Already is an old people mayhem sandbox game created by the designers of Goat Simulator. You are old and angry and you've just been kicked out of your retirement home. How will you survive in a world that wants you to Just Die Already?",
  "size": "",
  "vertical_artwork": "https://images.gog.com/dcfc9a8fc07912874bd9cd329760619f49881367daafbbbba9b407f14c42caac.jpg?namespace=gamesdb",
  "banner_image": "https://images.gog.com/56d0b7e66187906b17f7028e46abceacb88da3f9cbf0c88dba1257b6d9938c9a.jpg?namespace=gamesdb",
  "icon_image": "https://images.gog.com/b704dceb7856f4d36b1f1b71a281d4a5411b11e5463bc7d817e78f62ce5c2e8f.jpg?namespace=gamesdb",
  "steamId": "979070",
  "game_modes": [
    "Single player",
    "Co-operative",
    "Multiplayer"
  ],
  "languages": [
    "English"
  ],
  "tested": true,
  "owned": true,
  "is_featured": false,
  "created_at": "2025-08-01T02:40:48.201Z",
  "updated_at": "2025-08-11T06:42:51.332Z"
}