{
  "id": "2384c45f-48ca-4877-9efd-d94bcabb93bc",
  "title": "League of Legends",
  "storefront": "Epic",
  "databaseId": "64b0c77d07f644e6a2326a1fd7ab9926",
  "slug": "league-of-legends",
  "publisher": "Riot Games, Inc.  ",
  "developer": "Riot Games, Inc.  ",
  "release_date": "2021-11-04",
  "genre": "Action, RPG, Strategy",
  "languages": [
    "English"
  ],
  "game_modes": [
    "Co-operative",
    "Multiplayer"
  ],
  "size": null,
  "age_rating_summary": "ESRB Teen",
  "tags_structured": [
    {
      "id": "1216",
      "name": "Action"
    },
    {
      "id": "21122",
      "name": "Diverse Characters"
    },
    {
      "id": "21125",
      "name": "Competitive Community"
    },
    {
      "id": "21129",
      "name": "Challenging Combat"
    },
    {
      "id": "9547",
      "name": "Windows"
    },
    {
      "id": "1264",
      "name": "Co-op"
    },
    {
      "id": "1203",
      "name": "Multiplayer"
    },
    {
      "id": "1299",
      "name": "Competitive"
    },
    {
      "id": "21139",
      "name": "Amazing Characters"
    },
    {
      "id": "21140",
      "name": "Amazing Storytelling"
    },
    {
      "id": "1367",
      "name": "RPG"
    },
    {
      "id": "1370",
      "name": "Single Player"
    },
    {
      "id": "1115",
      "name": "Strategy"
    },
    {
      "id": "10719",
      "name": "Mac OS"
    }
  ],
  "genres_structured": [
    {
      "id": "1216",
      "name": "Action"
    },
    {
      "id": "1367",
      "name": "RPG"
    },
    {
      "id": "1115",
      "name": "Strategy"
    }
  ],
  "description": "League of Legends is a fast-paced, competitive online game that blends the speed and intensity of an RTS with RPG elements. Two teams of powerful champions, each with a unique design and playstyle, battle head-to-head across multiple battlefields and game modes. With an ever-expanding roster of champions, frequent updates and a thriving tournament scene, League of Legends offers endless replayability for players of every skill level.",
  "vertical_artwork": "https://images.gog.com/cffbae4e906a7cc71b7c33d97c702f294094178d482171ae5605708b25dcfb21.jpg?namespace=gamesdb",
  "banner_image": "https://images.gog.com/20304a368a1fd81d7eb4c46397375a4434a2878a6cfa28b158d9bf01441678a0.jpg?namespace=gamesdb",
  "icon_image": "https://images.gog.com/1642a42e55ae8e3215adacf491409ed328c375ffcb2b08f1b40a4dfe86ac315f.jpg?namespace=gamesdb",
  "epic_url": "",
  "steamId": "20590",
  "hltb_url": "https://howlongtobeat.com/game/5203",
  "hltb_id": "5203",
  "pcgamingwiki_url": "https://www.pcgamingwiki.com/wiki/League_of_Legends",
  "protondb_url": "https://www.protondb.com/app/20590",
  "requires_eos": true,
  "supports_eos": false,
  "epic_achievements": false,
  "epic_offline_mode": false,
  "controller_input": "",
  "requires_eac_runtime": false,
  "requires_battleye_runtime": false,
  "notes": "Imported from library - not yet tested",
  "date_tested": "",
  "proton_version": "",
  "decky_rating": "",
  "standalone_rating": "",
  "dependencies": "",
  "controller_config": "",
  "performance_notes": "",
  "known_issues": "",
  "set_executable": "",
  "required_launcher": "",
  "requires_account_setup": false,
  "account_type": "",
  "requires_verification": false,
  "cant_test_linux": true,
  "community_layout": false,
  "description_rich": "Become a legend. Find your champion, master their abilities, and outplay your opponents in an epic 5v5 battle to destroy the enemy base.    ",
  "use_rich_description": true
}
