{
  "id": "c4d2b1aa-bdc7-4a68-9cb3-8416d0ce48fa",
  "title": "Neko Ghost, Jump!",
  "storefront": "Epic",
  "protondb": "https://www.protondb.com/app/1194750",
  "gog_url": "",
  "epic_url": "",
  "itch_url": "",
  "notes": "Native controller support **Decky Plugin: Works out of the box**. **2.0 Standalone: Works out of the box**.",
  "date_tested": "March '25",
  "decky_rating": "green",
  "standalone_rating": "green",
  "proton_version": "",
  "dependencies": "",
  "controller_config": "Native Steam Deck Controls",
  "performance_notes": "",
  "known_issues": "",
  "requires_eos": false,
  "supports_eos": false,
  "requires_verification": false,
  "epic_achievements": false,
  "epic_offline_mode": false,
  "must_be_online": false,
  "requires_eac_runtime": false,
  "requires_battleye_runtime": false,
  "required_launcher": "",
  "requires_account_setup": false,
  "account_type": "",
  "controller_input": "native",
  "community_layout": false,
  "cant_test_linux": false,
  "databaseId": "a9999cf992d74279b410a0ac9608e153",
  "shortname": "a9999cf992d74279b410a0ac9608e153",
  "publisher": "Burgos Games",
  "developer": "Burgos Games",
  "releasedate": "2022-01-11T00:00:00+0000",
  "genre": "Adventure, Indie, Platform, Puzzle, Racing",
  "description": "Neko Ghost, Jump! is a puzzle-platformer where you not only switch between 2D & 3D camera perspectives but also between your physical & ghost forms to solve puzzles, combat enemies, and clear levels faster.",
  "size": "",
  "vertical_artwork": "https://images.gog.com/fe62da8c8d50c93c8c67e3256d9ee0a7805e43c7ac97bcc490654a373c1eb3ea.jpg?namespace=gamesdb",
  "banner_image": "https://images.gog.com/870d8fe35ab069486985bd673720e61dc2894cba70516107cfb7048eb205774c.jpg?namespace=gamesdb",
  "icon_image": "https://images.gog.com/591d179b15a312cc70ecf685dcbaf3117c5d1361c27a651109ebc4f3c5bac849.jpg?namespace=gamesdb",
  "steamId": "1194750",
  "game_modes": [
    "Single player"
  ],
  "languages": [
    "English"
  ],
  "owned": true,
  "is_featured": false,
  "created_at": "2025-08-01T02:40:48.201Z",
  "updated_at": "2025-08-01T04:08:36.968Z"
}