{
  "id": "d9d3899e-1517-47fe-b757-8f7edc9e151d",
  "title": "Redout: Enhanced Edition",
  "storefront": "Epic",
  "databaseId": "1be5efb848844b1dabf9d67f8017a7ae",
  "slug": "redout-enhanced-edition",
  "publisher": "Saber Interactive",
  "developer": "34BigThings SRL  ",
  "release_date": "2022-05-12",
  "genre": "Racing",
  "languages": [
    "English"
  ],
  "game_modes": [
    "Single player",
    "Co-operative",
    "Multiplayer"
  ],
  "size": null,
  "tags_structured": [
    {
      "id": "1264",
      "name": "Co-op"
    },
    {
      "id": "21121",
      "name": "Great for Quick Sessions"
    },
    {
      "id": "21138",
      "name": "Recommend this Game"
    },
    {
      "id": "1203",
      "name": "Multiplayer"
    },
    {
      "id": "21125",
      "name": "Competitive Community"
    },
    {
      "id": "19847",
      "name": "Achievements"
    },
    {
      "id": "1370",
      "name": "Single Player"
    },
    {
      "id": "9547",
      "name": "Windows"
    },
    {
      "id": "1212",
      "name": "Racing"
    },
    {
      "id": "9549",
      "name": "Controller Support"
    },
    {
      "id": "21149",
      "name": "Quickly Understand the Controls"
    }
  ],
  "genres_structured": [
    {
      "id": "1212",
      "name": "Racing"
    }
  ],
  "franchise": "Redout",
  "description": "Redout is a tribute to the old racing monsters such as F-Zero, WipeOut, Rollcage, and POD. It is designed to be an uncompromising, fast, tough and satisfying driving experience, soaked in that vertigo that stands at the core of the arcade racing genre.",
  "vertical_artwork": "https://images.gog.com/fdb6dd51ba8954c729f738926c24443b9c35f025afbe896b12df470138c59328.jpg?namespace=gamesdb",
  "banner_image": "https://images.gog.com/a42f7dae65082cd4ae7110b87cce2d2a036c1fb4a5c025876aea361f1ac7175f.jpg?namespace=gamesdb",
  "icon_image": "https://images.gog.com/6ce5d21c29eb567ffa77c4f8edf1c9eadc6612158a7687ca2fbfd14224206f5d.jpg?namespace=gamesdb",
  "epic_url": "https://store.epicgames.com/en-US/p/redout-enhanced-edition",
  "steamId": "517710",
  "hltb_url": "https://howlongtobeat.com/game/39800",
  "hltb_id": 39800,
  "hltb_main": "10.1 hrs",
  "hltb_main_extra": "20.4 hrs",
  "hltb_completionist": "49.8 hrs",
  "metacritic_score": 81,
  "metacritic_url": "https://www.metacritic.com/game/pc/redout-2016?ftag=MCD-06-10aaa1f",
  "pcgamingwiki_url": "https://www.pcgamingwiki.com/wiki/Redout",
  "protondb_url": "https://www.protondb.com/app/517710",
  "requires_eos": true,
  "supports_eos": false,
  "epic_achievements": false,
  "epic_offline_mode": false,
  "controller_input": "native",
  "requires_eac_runtime": false,
  "requires_battleye_runtime": false,
  "notes": "Native controller support. **Decky Plugin: Some tinkering required**. **Pro Version: Works out of the box**. Install C++ Runtime Install.",
  "date_tested": "Nov '24",
  "proton_version": "",
  "decky_rating": "yellow",
  "standalone_rating": "green",
  "dependencies": "<a href=\"https://learn.microsoft.com/en-us/cpp/windows/latest-supported-vc-redist?view=msvc-170\" target=\"_blank\" rel=\"noopener noreferrer\">Visual C++ Redistributable</a>",
  "controller_config": "",
  "performance_notes": "",
  "known_issues": "",
  "set_executable": "",
  "required_launcher": "",
  "requires_account_setup": false,
  "account_type": "",
  "requires_verification": false,
  "cant_test_linux": false,
  "community_layout": false,
  "was_free_before": true,
  "giveaway_events": [
    {
      "start": "2022-05-11T15:00:00.000Z",
      "end": "2022-05-18T15:00:00.000Z",
      "type": null,
      "id": "c82ab1b8b43843e6a279128614667fb8"
    }
  ],
  "description_rich": "NEXT GENERATION AG RACING IS HERE!\nRedout is a tribute to the classic racing monsters. It is designed to be an uncompromising, fast, tough and satisfying driving experience, soaked in that vertigo that stands at the core of the arcade racing genre.",
  "use_rich_description": true
}
