{
  "id": "15f5d27a-3825-41ab-94f4-518d0ef1130b",
  "title": "Slain: Back from Hell",
  "storefront": "Epic",
  "databaseId": "d8a4c98b5020483881eb7f0c3fc4cea3",
  "slug": "slain-back-from-hell",
  "publisher": "Digerati",
  "developer": "Steel Mantis",
  "release_date": "2022-10-06",
  "genre": "Action, Platformer, Indie",
  "languages": [
    "English"
  ],
  "game_modes": [
    "Single player"
  ],
  "size": null,
  "age_rating_summary": "ESRB Teen",
  "tags_structured": [
    {
      "id": "1216",
      "name": "Action"
    },
    {
      "id": "21109",
      "name": "Great Boss Battles"
    },
    {
      "id": "19847",
      "name": "Achievements"
    },
    {
      "id": "1370",
      "name": "Single Player"
    },
    {
      "id": "9547",
      "name": "Windows"
    },
    {
      "id": "1151",
      "name": "Platformer"
    },
    {
      "id": "1263",
      "name": "Indie"
    }
  ],
  "genres_structured": [
    {
      "id": "1216",
      "name": "Action"
    },
    {
      "id": "1151",
      "name": "Platformer"
    },
    {
      "id": "1263",
      "name": "Indie"
    }
  ],
  "description": "Slain: Back from Hell. A heavy metal inspired arcade combat with puzzle elements and gore galore. Stunning visuals and true old school gameplay accompanied by the most metal soundtrack you've ever heard.",
  "vertical_artwork": "https://images.gog.com/07fb597cdc7723ebdae42cfc91cd20a99700ad82e1a7ea5cdcf2f74db12df252.jpg?namespace=gamesdb",
  "banner_image": "https://images.gog.com/878ccf1f170e0ba4f62bbb835e61ae00767cbdcf6960647060e5bef7efe00152.jpg?namespace=gamesdb",
  "epic_url": "https://store.epicgames.com/en-US/p/slain-aea303",
  "steamId": "369070",
  "hltb_url": "https://howlongtobeat.com/game/40103",
  "hltb_id": 40103,
  "hltb_main": "6 hrs",
  "hltb_main_extra": "8.5 hrs",
  "hltb_completionist": "11.5 hrs",
  "metacritic_score": 74,
  "metacritic_url": "https://www.metacritic.com/game/pc/slain-back-from-hell?ftag=MCD-06-10aaa1f",
  "pcgamingwiki_url": "https://www.pcgamingwiki.com/wiki/Slain%3A_Back_from_Hell",
  "protondb_url": "https://www.protondb.com/app/369070",
  "controller_input": "native",
  "notes": "Works out of the box!",
  "date_tested": "March '25",
  "proton_version": "",
  "decky_rating": "green",
  "standalone_rating": "green",
  "dependencies": "",
  "controller_config": "Native Steam Deck Controls",
  "performance_notes": "",
  "known_issues": "",
  "was_free_before": true,
  "giveaway_events": [
    {
      "start": "2022-10-05T15:00:00.000Z",
      "end": "2022-10-12T15:00:00.000Z",
      "type": null,
      "id": "e5267e621ed14b84829c82a69e289c8e"
    }
  ],
  "description_rich": "A heavy metal inspired arcade combat with puzzle elements and gore galore. Stunning visuals and true old school gameplay accompanied by the most metal soundtrack you've ever heard.",
  "use_rich_description": true
}
